stash/__init__.py
stash/settings.py
stash/types.py
stash/utils.py
tests/__init__.py
tests/tests.py
stash_cache-0.0.2.dist-info/LICENSE
stash_cache-0.0.2.dist-info/METADATA
stash_cache-0.0.2.dist-info/WHEEL
stash_cache-0.0.2.dist-info/top_level.txt
stash_cache-0.0.2.dist-info/RECORD
