Metadata-Version: 2.1
Name: stash-cache
Version: 0.0.2
Summary: Stash helps you to safely persist your function cache.
Home-page: UNKNOWN
Author: Vikram Cothur
Author-email: vcothur7@gmail.com
License: UNKNOWN
Keywords: python,cache,persistent,stash,function,stash cache
Platform: UNKNOWN
Classifier: Development Status :: 3 - Alpha
Classifier: Programming Language :: Python :: 2
Classifier: Programming Language :: Python :: 3
Classifier: Operating System :: MacOS :: MacOS X
Classifier: Operating System :: Microsoft :: Windows
License-File: LICENSE
Provides-Extra: dev
Requires-Dist: pytest (>=3.7) ; extra == 'dev'
